[
    {
        "date": "2025-08-20",
        "pagesRead": 77,
        "bookTitle": "데이터 중심 애플리케이션 설계"
    },
    {
        "date": "2025-08-20",
        "pagesRead": 47,
        "bookTitle": "의지와 표상으로서의 세계"
    },
    {
        "date": "2025-08-21",
        "pagesRead": 30,
        "bookTitle": "데이터 중심 애플리케이션 설계"
    },
    {
        "date": "2025-08-21",
        "pagesRead": 62,
        "bookTitle": "로버트 나이스트롬의 인터프리터 in Java, C"
    },
    {
        "date": "2025-08-22",
        "pagesRead": 83,
        "bookTitle":"데이터 중심 애플리케이션 설계"
    },
    {
        "date": "2025-08-23",
        "pagesRead": 56,
        "bookTitle": "구조주의와 그 이후"
    },
    {
        "date": "2025-08-25",
        "pagesRead" : 50,
        "bookTitle": "노인과 바다"
    },
    {
        "date": "2025-08-26",
        "pagesRead": 71,
        "bookTitle": "데이터 중심 애플리케이션 설계"
    },
    {
        "date": "2025-08-27",
        "pagesRead": 94,
        "bookTitle":"데이터 중심 애플리케이션 설계" 
    },
    {
        "date": "2025-08-27",
        "pagesRead": 48,
        "bookTitle":"로버트 나이스트롬의 인터프리터 in Java, C"
    },
    {
        "date": "2025-08-28",
        "pagesRead": 92,
        "bookTitle": "JVM 밑바닥까지 파헤치기"
    },
    {
        "date": "2025-08-28",
        "pagesRead": 40,
        "bookTitle": "데이터 중심 애플리케이션 설계"
    },
    {
        "date": "2025-09-02",
        "pagesRead": 50,
        "bookTitle": "노인과 바다"
    },
    {
        "date": "2025-09-03",
        "pagesRead": 12,
        "bookTitle": "데이터 중심 애플리케이션 설계"
    },
    {
        "date": "2025-09-06",
        "pagesRead": 25,
        "bookTitle": "노인과 바다"
    },
    {
        "date": "2025-09-08",
        "pagesRead": 13,
        "bookTitle": "Architecture of a Database System"
    },
    {
        "date": "2025-09-09",
        "pagesRead": 30,
        "bookTitle": "Architecture of a Database System"
    },
    {
        "date": "2025-09-10",
        "pagesRead": 49,
        "bookTitle": "시지프 신화"
    },
    {
        "date": "2025-09-12",
        "pagesRead": 28,
        "bookTitle": "Architecture of a Database System"
    },
    {
        "date": "2025-09-12",
        "pagesRead": 26,
        "bookTitle": "Architecture of a Database System"
    },
    {
        "date": "2025-10-16",
        "pagesRead": 32,
        "bookTitle": "도덕 형이상학을 위한 기초 놓기"
    },
    {
        "date": "2025-10-17",
        "pagesRead": 48,
        "bookTitle": "도덕 형이상학을 위한 기초 놓기"
    },
    {
        "date": "2025-10-21",
        "pagesRead": 51,
        "bookTitle": "정신분석 강의"
    },
    {
        "date": "2025-10-22",
        "pagesRead": 100,
        "bookTitle": "인형의 집"
    },
    {
        "date": "2025-10-23",
        "pagesRead": 21,
        "bookTitle": "JVM 밑바닥까지 파헤치기"
    },
    {
        "date": "2025-10-23",
        "pagesRead": 41,
        "bookTitle": "구토"
    }
]